Workbook

Sheet Bank Reconciliation Statement
A1: June 2026 Bank Reconciliation
A2: Reconciled from the cleaned bank statement and GL cash extract
A3: Reconciliation bridge | B3: Amount | C3: Count
A4: Bank activity total | B4: =SUM(Bankl[Amount]) -> 222907.3 | C4: 122
A5: GL activity total | B5: =SUM(Cash[Amount]) -> 253663.77 | C5: 121
A6: Raw GL less bank | B6: =B5-B4 -> 30756.47
A7: Less: GL-only transactions | B7: =-SUMIFS(Cash[Amount],Cash[Reconciliation Status],"Missing from Bank") -> -31253.55 | C7: =COUNTIF(Cash[Reconciliation Status],"Missing from Bank") -> 6
A8: Add: Bank-only transactions | B8: =SUMIFS(Bankl[Amount],Bankl[Reconciliation Status],"Missing from GL") -> 497.43 | C8: =COUNTIF(Bankl[Reconciliation Status],"Missing from GL") -> 7
A9: Add: Bank–GL amount differences | B9: =SUMIFS(Bankl[Difference],Bankl[Reconciliation Status],"Difference") -> -0.35 | C9: =COUNTIF(Bankl[Reconciliation Status],"Difference") -> 8
A10: Adjusted GL activity | B10: =B5+B7+B8+B9 -> 222907.3
A11: Unreconciled variance | B11: =B4-B10 -> 0
A13: Exception Type | B13: Date | C13: Reference | D13: Description / Memo | E13: Bank Amount | F13: GL Amount | G13: Suggested Action
A14: Amount Difference | B14: 46177 | C14: REF40826 | D14: EFT BELL CDA PAYMENT REF40826 | E14: -4183.58 | F14: -4183.67 | G14: Verify source and adjust GL to bank amount; bank–GL variance $0.09
A15: Amount Difference | B15: 46183 | C15: REF40929 | D15: PAD GFL ENVIRONMENTAL SVC REF40929 | E15: -743.6 | F15: -743.29 | G15: Verify source and adjust GL to bank amount; bank–GL variance -$0.31
A16: Amount Difference | B16: 46190 | C16: REF40833 | D16: PAD SHELL FLEET CARD SVC REF40833 | E16: -2411.46 | F16: -2411.28 | G16: Verify source and adjust GL to bank amount; bank–GL variance -$0.18
A17: Bank Only | B17: 46191 | C17: NSF-0618 | D17: NSF RETURNED ITEM FEE | E17: -48 | G17: Post bank fee/charge to the GL
A18: Amount Difference | B18: 46191 | C18: REF40918 | D18: PAD MILTON HYDRO UTIL REF40918 | E18: -1154.68 | F18: -1154.82 | G18: Verify source and adjust GL to bank amount; bank–GL variance $0.14
A19: Amount Difference | B19: 46195 | C19: REF40901 | D19: EFT ANIXTER CDA SUPPLY REF40901 | E19: -9274.79 | F19: -9274.16 | G19: Verify source and adjust GL to bank amount; bank–GL variance -$0.63
A20: Bank Only | B20: 46195 | C20: MER-0622 | D20: MERCHANT PROCESSING FEE MONERIS | E20: -389.44 | G20: Post bank fee/charge to the GL
A21: Amount Difference | B21: 46195 | C21: REF40884 | D21: PAD INTACT INSURANCE PREM REF40884 | E21: -1887.08 | F21: -1887.53 | G21: Verify source and adjust GL to bank amount; bank–GL variance $0.45
A22: Amount Difference | B22: 46195 | C22: REF40865 | D22: PAD UNITED RENTALS INC REF40865 | E22: -6649.18 | F22: -6648.91 | G22: Verify source and adjust GL to bank amount; bank–GL variance -$0.27
A23: Amount Difference | B23: 46197 | C23: REF40852 | D23: EFT WESCO DIST CANADA REF40852 | E23: -13902.08 | F23: -13902.44 | G23: Verify source and adjust GL to bank amount; bank–GL variance $0.36
A24: Bank Only | B24: 46198 | C24: PAD-7719 | D24: PRE-AUTH DEBIT UNKNOWN ORIG 7719 | E24: -1260 | G24: Investigate the bank-only transaction and post if valid
A25: Bank Only | B25: 46199 | C25: ETR-T4X99A | D25: E-TRANSFER RECEIVED T4X99A | E25: 2150 | G25: Post bank fee/charge to the GL
A26: Bank Only | B26: 46203 | C26: INT-JUN | D26: INTEREST EARNED | E26: 214.87 | G26: Post bank interest income to the GL
A27: Bank Only | B27: 46203 | C27: SVC-JUN | D27: MONTHLY ACCOUNT FEE | E27: -125 | G27: Post bank fee/charge to the GL
A28: Bank Only | B28: 46203 | C28: WIRE-FEE | D28: SERVICE CHARGE - WIRE PAYMENT | E28: -45 | G28: Post bank fee/charge to the GL
A29: GL Only | B29: 46199 | C29: CHQ#1079 | D29: Ditch Witch of Ontario — parts invoice | F29: -7412.66 | G29: Outstanding payment—confirm it cleared after June
A30: GL Only | B30: 46202 | C30: CHQ#1081 | D30: Region of Halton — road permit fees | F30: -2340.55 | G30: Outstanding payment—confirm it cleared after June
A31: GL Only | B31: 46202 | C31: CHQ#1080 | D31: Vermeer Canada — drill head rebuild | F31: -15890.23 | G31: Outstanding payment—confirm it cleared after June
A32: GL Only | B32: 46203 | C32: CHQ#1082 | D32: Brandt Tractor Ltd — service invoice | F32: -4178.09 | G32: Outstanding payment—confirm it cleared after June
A33: GL Only | B33: 46203 | C33: REF40957 | D33: Cogeco underground build | F33: 12764.31 | G33: Deposit in transit—confirm bank receipt after June
A34: GL Only | B34: 46203 | C34: REF40947 | D34: Rogers Communications — progress billing | F34: 48310.77 | G34: Deposit in transit—confirm bank receipt after June

Sheet bank_statement_jun2026
A1: Date | B1: Description | C1: Reference | D1: Amount | E1: GL MATCH | F1: Reconciliation Status | G1: Difference | H1: Action / Notes
A2: 46174 | B2: CHEQUE 1042 | C2: CHQ#1042 | D2: -10230.18 | E2: =_xlfn.XLOOKUP(C2,gl_cash_extract_jun2026!D:D,gl_cash_extract_jun2026!E:E,"Not Found") -> -10230.18 | F2: =IF(E2="Not Found","Missing from GL",IF(D2=E2,"Matched","Difference")) -> Matched | G2: =IF(ISNUMBER(E2),ROUND(D2-E2,2),"") -> 0
A3: 46174 | B3: CHEQUE 1064 | C3: CHQ#1064 | D3: -8067.99 | E3: =_xlfn.XLOOKUP(C3,gl_cash_extract_jun2026!D:D,gl_cash_extract_jun2026!E:E,"Not Found") -> -8067.99 | F3: =IF(E3="Not Found","Missing from GL",IF(D3=E3,"Matched","Difference")) -> Matched | G3: =IF(ISNUMBER(E3),ROUND(D3-E3,2),"") -> 0
A4: 46174 | B4: DEP ROGERS COMM AP REF40771 | C4: REF40771 | D4: 88790.68 | E4: =_xlfn.XLOOKUP(C4,gl_cash_extract_jun2026!D:D,gl_cash_extract_jun2026!E:E,"Not Found") -> 88790.68 | F4: =IF(E4="Not Found","Missing from GL",IF(D4=E4,"Matched","Difference")) -> Matched | G4: =IF(ISNUMBER(E4),ROUND(D4-E4,2),"") -> 0
A5: 46174 | B5: PAD SHELL FLEET REF40144 | C5: REF40144 | D5: -12217.56 | E5: =_xlfn.XLOOKUP(C5,gl_cash_extract_jun2026!D:D,gl_cash_extract_jun2026!E:E,"Not Found") -> -12217.56 | F5: =IF(E5="Not Found","Missing from GL",IF(D5=E5,"Matched","Difference")) -> Matched | G5: =IF(ISNUMBER(E5),ROUND(D5-E5,2),"") -> 0
A6: 46175 | B6: CHEQUE 1051 | C6: CHQ#1051 | D6: -17040.77 | E6: =_xlfn.XLOOKUP(C6,gl_cash_extract_jun2026!D:D,gl_cash_extract_jun2026!E:E,"Not Found") -> -17040.77 | F6: =IF(E6="Not Found","Missing from GL",IF(D6=E6,"Matched","Difference")) -> Matched | G6: =IF(ISNUMBER(E6),ROUND(D6-E6,2),"") -> 0
A7: 46175 | B7: DEP TELUS COMM AP REF40191 | C7: REF40191 | D7: 88411.47 | E7: =_xlfn.XLOOKUP(C7,gl_cash_extract_jun2026!D:D,gl_cash_extract_jun2026!E:E,"Not Found") -> 88411.47 | F7: =IF(E7="Not Found","Missing from GL",IF(D7=E7,"Matched","Difference")) -> Matched | G7: =IF(ISNUMBER(E7),ROUND(D7-E7,2),"") -> 0
A8: 46175 | B8: PAD ENTERPRISE FLEET REF40486 | C8: REF40486 | D8: -5365.64 | E8: =_xlfn.XLOOKUP(C8,gl_cash_extract_jun2026!D:D,gl_cash_extract_jun2026!E:E,"Not Found") -> -5365.64 | F8: =IF(E8="Not Found","Missing from GL",IF(D8=E8,"Matched","Difference")) -> Matched | G8: =IF(ISNUMBER(E8),ROUND(D8-E8,2),"") -> 0
A9: 46176 | B9: CHEQUE 1048 | C9: CHQ#1048 | D9: -21094.19 | E9: =_xlfn.XLOOKUP(C9,gl_cash_extract_jun2026!D:D,gl_cash_extract_jun2026!E:E,"Not Found") -> -21094.19 | F9: =IF(E9="Not Found","Missing from GL",IF(D9=E9,"Matched","Difference")) -> Matched | G9: =IF(ISNUMBER(E9),ROUND(D9-E9,2),"") -> 0
A10: 46176 | B10: DEP ROGERS COMM AP REF40398 | C10: REF40398 | D10: 102367.19 | E10: =_xlfn.XLOOKUP(C10,gl_cash_extract_jun2026!D:D,gl_cash_extract_jun2026!E:E,"Not Found") -> 102367.19 | F10: =IF(E10="Not Found","Missing from GL",IF(D10=E10,"Matched","Difference")) -> Matched | G10: =IF(ISNUMBER(E10),ROUND(D10-E10,2),"") -> 0
A11: 46176 | B11: EFT BRANDT TRACTOR REF40276 | C11: REF40276 | D11: -12316.92 | E11: =_xlfn.XLOOKUP(C11,gl_cash_extract_jun2026!D:D,gl_cash_extract_jun2026!E:E,"Not Found") -> -12316.92 | F11: =IF(E11="Not Found","Missing from GL",IF(D11=E11,"Matched","Difference")) -> Matched | G11: =IF(ISNUMBER(E11),ROUND(D11-E11,2),"") -> 0
A12: 46176 | B12: PAD MILTON HYDRO REF40442 | C12: REF40442 | D12: -20094.18 | E12: =_xlfn.XLOOKUP(C12,gl_cash_extract_jun2026!D:D,gl_cash_extract_jun2026!E:E,"Not Found") -> -20094.18 | F12: =IF(E12="Not Found","Missing from GL",IF(D12=E12,"Matched","Difference")) -> Matched | G12: =IF(ISNUMBER(E12),ROUND(D12-E12,2),"") -> 0
A13: 46177 | B13: EFT BELL CDA PAYMENT REF40826 | C13: REF40826 | D13: -4183.58 | E13: =_xlfn.XLOOKUP(C13,gl_cash_extract_jun2026!D:D,gl_cash_extract_jun2026!E:E,"Not Found") -> -4183.67 | F13: =IF(E13="Not Found","Missing from GL",IF(D13=E13,"Matched","Difference")) -> Difference | G13: =IF(ISNUMBER(E13),ROUND(D13-E13,2),"") -> 0.09 | H13: Verify source and adjust GL to bank amount; bank–GL variance $0.09
A14: 46177 | B14: EFT BRANDT TRACTOR REF40587 | C14: REF40587 | D14: -6479.58 | E14: =_xlfn.XLOOKUP(C14,gl_cash_extract_jun2026!D:D,gl_cash_extract_jun2026!E:E,"Not Found") -> -6479.58 | F14: =IF(E14="Not Found","Missing from GL",IF(D14=E14,"Matched","Difference")) -> Matched | G14: =IF(ISNUMBER(E14),ROUND(D14-E14,2),"") -> 0
A15: 46177 | B15: EFT WESCO DIST REF40326 | C15: REF40326 | D15: -12272.98 | E15: =_xlfn.XLOOKUP(C15,gl_cash_extract_jun2026!D:D,gl_cash_extract_jun2026!E:E,"Not Found") -> -12272.98 | F15: =IF(E15="Not Found","Missing from GL",IF(D15=E15,"Matched","Difference")) -> Matched | G15: =IF(ISNUMBER(E15),ROUND(D15-E15,2),"") -> 0
A16: 46177 | B16: PAD SHELL FLEET REF40128 | C16: REF40128 | D16: -3503.79 | E16: =_xlfn.XLOOKUP(C16,gl_cash_extract_jun2026!D:D,gl_cash_extract_jun2026!E:E,"Not Found") -> -3503.79 | F16: =IF(E16="Not Found","Missing from GL",IF(D16=E16,"Matched","Difference")) -> Matched | G16: =IF(ISNUMBER(E16),ROUND(D16-E16,2),"") -> 0
A17: 46178 | B17: DEP BELL CDA AP REF40634 | C17: REF40634 | D17: 77425.86 | E17: =_xlfn.XLOOKUP(C17,gl_cash_extract_jun2026!D:D,gl_cash_extract_jun2026!E:E,"Not Found") -> 77425.86 | F17: =IF(E17="Not Found","Missing from GL",IF(D17=E17,"Matched","Difference")) -> Matched | G17: =IF(ISNUMBER(E17),ROUND(D17-E17,2),"") -> 0
A18: 46178 | B18: PAD GFL ENVIRONMENTAL REF40334 | C18: REF40334 | D18: -14685.67 | E18: =_xlfn.XLOOKUP(C18,gl_cash_extract_jun2026!D:D,gl_cash_extract_jun2026!E:E,"Not Found") -> -14685.67 | F18: =IF(E18="Not Found","Missing from GL",IF(D18=E18,"Matched","Difference")) -> Matched | G18: =IF(ISNUMBER(E18),ROUND(D18-E18,2),"") -> 0
A19: 46178 | B19: PAD SHELL FLEET REF40539 | C19: REF40539 | D19: -6506.94 | E19: =_xlfn.XLOOKUP(C19,gl_cash_extract_jun2026!D:D,gl_cash_extract_jun2026!E:E,"Not Found") -> -6506.94 | F19: =IF(E19="Not Found","Missing from GL",IF(D19=E19,"Matched","Difference")) -> Matched | G19: =IF(ISNUMBER(E19),ROUND(D19-E19,2),"") -> 0
A20: 46181 | B20: CHEQUE 1050 | C20: CHQ#1050 | D20: -3062.32 | E20: =_xlfn.XLOOKUP(C20,gl_cash_extract_jun2026!D:D,gl_cash_extract_jun2026!E:E,"Not Found") -> -3062.32 | F20: =IF(E20="Not Found","Missing from GL",IF(D20=E20,"Matched","Difference")) -> Matched | G20: =IF(ISNUMBER(E20),ROUND(D20-E20,2),"") -> 0
A21: 46181 | B21: CHEQUE 1053 | C21: CHQ#1053 | D21: -19414.58 | E21: =_xlfn.XLOOKUP(C21,gl_cash_extract_jun2026!D:D,gl_cash_extract_jun2026!E:E,"Not Found") -> -19414.58 | F21: =IF(E21="Not Found","Missing from GL",IF(D21=E21,"Matched","Difference")) -> Matched | G21: =IF(ISNUMBER(E21),ROUND(D21-E21,2),"") -> 0
A22: 46181 | B22: CHEQUE 1058 | C22: CHQ#1058 | D22: -2088.26 | E22: =_xlfn.XLOOKUP(C22,gl_cash_extract_jun2026!D:D,gl_cash_extract_jun2026!E:E,"Not Found") -> -2088.26 | F22: =IF(E22="Not Found","Missing from GL",IF(D22=E22,"Matched","Difference")) -> Matched | G22: =IF(ISNUMBER(E22),ROUND(D22-E22,2),"") -> 0
A23: 46181 | B23: CHEQUE 1063 | C23: CHQ#1063 | D23: -20631.69 | E23: =_xlfn.XLOOKUP(C23,gl_cash_extract_jun2026!D:D,gl_cash_extract_jun2026!E:E,"Not Found") -> -20631.69 | F23: =IF(E23="Not Found","Missing from GL",IF(D23=E23,"Matched","Difference")) -> Matched | G23: =IF(ISNUMBER(E23),ROUND(D23-E23,2),"") -> 0
A24: 46181 | B24: DEP BELL CDA AP REF40527 | C24: REF40527 | D24: 109123.56 | E24: =_xlfn.XLOOKUP(C24,gl_cash_extract_jun2026!D:D,gl_cash_extract_jun2026!E:E,"Not Found") -> 109123.56 | F24: =IF(E24="Not Found","Missing from GL",IF(D24=E24,"Matched","Difference")) -> Matched | G24: =IF(ISNUMBER(E24),ROUND(D24-E24,2),"") -> 0
A25: 46181 | B25: DEP BELL CDA AP REF40561 | C25: REF40561 | D25: 104277.78 | E25: =_xlfn.XLOOKUP(C25,gl_cash_extract_jun2026!D:D,gl_cash_extract_jun2026!E:E,"Not Found") -> 104277.78 | F25: =IF(E25="Not Found","Missing from GL",IF(D25=E25,"Matched","Difference")) -> Matched | G25: =IF(ISNUMBER(E25),ROUND(D25-E25,2),"") -> 0
... A42: 46182 | B42: PAD SHELL FLEET REF40147 | C42: REF40147 | D42: -10880.16 | E42: =_xlfn.XLOOKUP(C42,gl_cash_extract_jun2026!D:D,gl_cash_extract_jun2026!E:E,"Not Found") -> -10880.16 | F42: =IF(E42="Not Found","Missing from GL",IF(D42=E42,"Matched","Difference")) -> Matched | G42: =IF(ISNUMBER(E42),ROUND(D42-E42,2),"") -> 0
A43: 46183 | B43: PAD GFL ENVIRONMENTAL SVC REF40929 | C43: REF40929 | D43: -743.6 | E43: =_xlfn.XLOOKUP(C43,gl_cash_extract_jun2026!D:D,gl_cash_extract_jun2026!E:E,"Not Found") -> -743.29 | F43: =IF(E43="Not Found","Missing from GL",IF(D43=E43,"Matched","Difference")) -> Difference | G43: =IF(ISNUMBER(E43),ROUND(D43-E43,2),"") -> -0.31 | H43: Verify source and adjust GL to bank amount; bank–GL variance -$0.31
A44: 46184 | B44: CHEQUE 1046 | C44: CHQ#1046 | D44: -21055.08 | E44: =_xlfn.XLOOKUP(C44,gl_cash_extract_jun2026!D:D,gl_cash_extract_jun2026!E:E,"Not Found") -> -21055.08 | F44: =IF(E44="Not Found","Missing from GL",IF(D44=E44,"Matched","Difference")) -> Matched | G44: =IF(ISNUMBER(E44),ROUND(D44-E44,2),"") -> 0
A45: 46184 | B45: CHEQUE 1076 | C45: CHQ#1076 | D45: -9101.04 | E45: =_xlfn.XLOOKUP(C45,gl_cash_extract_jun2026!D:D,gl_cash_extract_jun2026!E:E,"Not Found") -> -9101.04 | F45: =IF(E45="Not Found","Missing from GL",IF(D45=E45,"Matched","Difference")) -> Matched | G45: =IF(ISNUMBER(E45),ROUND(D45-E45,2),"") -> 0
A46: 46184 | B46: DEP ROGERS COMM AP REF40691 | C46: REF40691 | D46: 41142.46 | E46: =_xlfn.XLOOKUP(C46,gl_cash_extract_jun2026!D:D,gl_cash_extract_jun2026!E:E,"Not Found") -> 41142.46 | F46: =IF(E46="Not Found","Missing from GL",IF(D46=E46,"Matched","Difference")) -> Matched | G46: =IF(ISNUMBER(E46),ROUND(D46-E46,2),"") -> 0
A47: 46184 | B47: DEP TELUS COMM AP REF40158 | C47: REF40158 | D47: 87832.55 | E47: =_xlfn.XLOOKUP(C47,gl_cash_extract_jun2026!D:D,gl_cash_extract_jun2026!E:E,"Not Found") -> 87832.55 | F47: =IF(E47="Not Found","Missing from GL",IF(D47=E47,"Matched","Difference")) -> Matched | G47: =IF(ISNUMBER(E47),ROUND(D47-E47,2),"") -> 0
A48: 46184 | B48: PAD INTACT INS REF40786 | C48: REF40786 | D48: -22782.19 | E48: =_xlfn.XLOOKUP(C48,gl_cash_extract_jun2026!D:D,gl_cash_extract_jun2026!E:E,"Not Found") -> -22782.19 | F48: =IF(E48="Not Found","Missing from GL",IF(D48=E48,"Matched","Difference")) -> Matched | G48: =IF(ISNUMBER(E48),ROUND(D48-E48,2),"") -> 0
A49: 46185 | B49: CHEQUE 1044 | C49: CHQ#1044 | D49: -10980.23 | E49: =_xlfn.XLOOKUP(C49,gl_cash_extract_jun2026!D:D,gl_cash_extract_jun2026!E:E,"Not Found") -> -10980.23 | F49: =IF(E49="Not Found","Missing from GL",IF(D49=E49,"Matched","Difference")) -> Matched | G49: =IF(ISNUMBER(E49),ROUND(D49-E49,2),"") -> 0
A50: 46185 | B50: CHEQUE 1070 | C50: CHQ#1070 | D50: -8175.43 | E50: =_xlfn.XLOOKUP(C50,gl_cash_extract_jun2026!D:D,gl_cash_extract_jun2026!E:E,"Not Found") -> -8175.43 | F50: =IF(E50="Not Found","Missing from GL",IF(D50=E50,"Matched","Difference")) -> Matched | G50: =IF(ISNUMBER(E50),ROUND(D50-E50,2),"") -> 0
A51: 46185 | B51: CHEQUE 1072 | C51: CHQ#1072 | D51: -14804.25 | E51: =_xlfn.XLOOKUP(C51,gl_cash_extract_jun2026!D:D,gl_cash_extract_jun2026!E:E,"Not Found") -> -14804.25 | F51: =IF(E51="Not Found","Missing from GL",IF(D51=E51,"Matched","Difference")) -> Matched | G51: =IF(ISNUMBER(E51),ROUND(D51-E51,2),"") -> 0
A52: 46185 | B52: EFT BRANDT TRACTOR REF40638 | C52: REF40638 | D52: -1176.36 | E52: =_xlfn.XLOOKUP(C52,gl_cash_extract_jun2026!D:D,gl_cash_extract_jun2026!E:E,"Not Found") -> -1176.36 | F52: =IF(E52="Not Found","Missing from GL",IF(D52=E52,"Matched","Difference")) -> Matched | G52: =IF(ISNUMBER(E52),ROUND(D52-E52,2),"") -> 0
A53: 46185 | B53: PAD ENTERPRISE FLEET REF40376 | C53: REF40376 | D53: -16179.58 | E53: =_xlfn.XLOOKUP(C53,gl_cash_extract_jun2026!D:D,gl_cash_extract_jun2026!E:E,"Not Found") -> -16179.58 | F53: =IF(E53="Not Found","Missing from GL",IF(D53=E53,"Matched","Difference")) -> Matched | G53: =IF(ISNUMBER(E53),ROUND(D53-E53,2),"") -> 0
A54: 46185 | B54: POS STAPLES BUS ADV REF40167 | C54: REF40167 | D54: -2483.78 | E54: =_xlfn.XLOOKUP(C54,gl_cash_extract_jun2026!D:D,gl_cash_extract_jun2026!E:E,"Not Found") -> -2483.78 | F54: =IF(E54="Not Found","Missing from GL",IF(D54=E54,"Matched","Difference")) -> Matched | G54: =IF(ISNUMBER(E54),ROUND(D54-E54,2),"") -> 0
A55: 46188 | B55: CHEQUE 1043 | C55: CHQ#1043 | D55: -12952.95 | E55: =_xlfn.XLOOKUP(C55,gl_cash_extract_jun2026!D:D,gl_cash_extract_jun2026!E:E,"Not Found") -> -12952.95 | F55: =IF(E55="Not Found","Missing from GL",IF(D55=E55,"Matched","Difference")) -> Matched | G55: =IF(ISNUMBER(E55),ROUND(D55-E55,2),"") -> 0
... A72: 46190 | B72: DEP BELL CDA AP REF40736 | C72: REF40736 | D72: 56603.15 | E72: =_xlfn.XLOOKUP(C72,gl_cash_extract_jun2026!D:D,gl_cash_extract_jun2026!E:E,"Not Found") -> 56603.15 | F72: =IF(E72="Not Found","Missing from GL",IF(D72=E72,"Matched","Difference")) -> Matched | G72: =IF(ISNUMBER(E72),ROUND(D72-E72,2),"") -> 0
A73: 46190 | B73: PAD SHELL FLEET CARD SVC REF40833 | C73: REF40833 | D73: -2411.46 | E73: =_xlfn.XLOOKUP(C73,gl_cash_extract_jun2026!D:D,gl_cash_extract_jun2026!E:E,"Not Found") -> -2411.28 | F73: =IF(E73="Not Found","Missing from GL",IF(D73=E73,"Matched","Difference")) -> Difference | G73: =IF(ISNUMBER(E73),ROUND(D73-E73,2),"") -> -0.18 | H73: Verify source and adjust GL to bank amount; bank–GL variance -$0.18
A74: 46191 | B74: ADP PAYROLL PPD REF40219 | C74: REF40219 | D74: -15305.18 | E74: =_xlfn.XLOOKUP(C74,gl_cash_extract_jun2026!D:D,gl_cash_extract_jun2026!E:E,"Not Found") -> -15305.18 | F74: =IF(E74="Not Found","Missing from GL",IF(D74=E74,"Matched","Difference")) -> Matched | G74: =IF(ISNUMBER(E74),ROUND(D74-E74,2),"") -> 0
A75: 46191 | B75: CHEQUE 1049 | C75: CHQ#1049 | D75: -15895.26 | E75: =_xlfn.XLOOKUP(C75,gl_cash_extract_jun2026!D:D,gl_cash_extract_jun2026!E:E,"Not Found") -> -15895.26 | F75: =IF(E75="Not Found","Missing from GL",IF(D75=E75,"Matched","Difference")) -> Matched | G75: =IF(ISNUMBER(E75),ROUND(D75-E75,2),"") -> 0
A76: 46191 | B76: CHEQUE 1055 | C76: CHQ#1055 | D76: -10735.37 | E76: =_xlfn.XLOOKUP(C76,gl_cash_extract_jun2026!D:D,gl_cash_extract_jun2026!E:E,"Not Found") -> -10735.37 | F76: =IF(E76="Not Found","Missing from GL",IF(D76=E76,"Matched","Difference")) -> Matched | G76: =IF(ISNUMBER(E76),ROUND(D76-E76,2),"") -> 0
A77: 46191 | B77: CHEQUE 1074 | C77: CHQ#1074 | D77: -4709.23 | E77: =_xlfn.XLOOKUP(C77,gl_cash_extract_jun2026!D:D,gl_cash_extract_jun2026!E:E,"Not Found") -> -4709.23 | F77: =IF(E77="Not Found","Missing from GL",IF(D77=E77,"Matched","Difference")) -> Matched | G77: =IF(ISNUMBER(E77),ROUND(D77-E77,2),"") -> 0
A78: 46191 | B78: DEP COGECO CONNEXION REF40357 | C78: REF40357 | D78: 111792.66 | E78: =_xlfn.XLOOKUP(C78,gl_cash_extract_jun2026!D:D,gl_cash_extract_jun2026!E:E,"Not Found") -> 111792.66 | F78: =IF(E78="Not Found","Missing from GL",IF(D78=E78,"Matched","Difference")) -> Matched | G78: =IF(ISNUMBER(E78),ROUND(D78-E78,2),"") -> 0
A79: 46191 | B79: DEP ROGERS COMM AP REF40295 | C79: REF40295 | D79: 86353.93 | E79: =_xlfn.XLOOKUP(C79,gl_cash_extract_jun2026!D:D,gl_cash_extract_jun2026!E:E,"Not Found") -> 86353.93 | F79: =IF(E79="Not Found","Missing from GL",IF(D79=E79,"Matched","Difference")) -> Matched | G79: =IF(ISNUMBER(E79),ROUND(D79-E79,2),"") -> 0
A80: 46191 | B80: DEP TELUS COMM AP REF40260 | C80: REF40260 | D80: 47196.48 | E80: =_xlfn.XLOOKUP(C80,gl_cash_extract_jun2026!D:D,gl_cash_extract_jun2026!E:E,"Not Found") -> 47196.48 | F80: =IF(E80="Not Found","Missing from GL",IF(D80=E80,"Matched","Difference")) -> Matched | G80: =IF(ISNUMBER(E80),ROUND(D80-E80,2),"") -> 0
A81: 46191 | B81: NSF RETURNED ITEM FEE | C81: NSF-0618 | D81: -48 | E81: =_xlfn.XLOOKUP(C81,gl_cash_extract_jun2026!D:D,gl_cash_extract_jun2026!E:E,"Not Found") -> Not Found | F81: =IF(E81="Not Found","Missing from GL",IF(D81=E81,"Matched","Difference")) -> Missing from GL | G81: =IF(ISNUMBER(E81),ROUND(D81-E81,2),"") | H81: Post bank fee/charge to the GL
A82: 46191 | B82: PAD ENTERPRISE FLEET REF40580 | C82: REF40580 | D82: -3937.53 | E82: =_xlfn.XLOOKUP(C82,gl_cash_extract_jun2026!D:D,gl_cash_extract_jun2026!E:E,"Not Found") -> -3937.53 | F82: =IF(E82="Not Found","Missing from GL",IF(D82=E82,"Matched","Difference")) -> Matched | G82: =IF(ISNUMBER(E82),ROUND(D82-E82,2),"") -> 0
A83: 46191 | B83: PAD MILTON HYDRO UTIL REF40918 | C83: REF40918 | D83: -1154.68 | E83: =_xlfn.XLOOKUP(C83,gl_cash_extract_jun2026!D:D,gl_cash_extract_jun2026!E:E,"Not Found") -> -1154.82 | F83: =IF(E83="Not Found","Missing from GL",IF(D83=E83,"Matched","Difference")) -> Difference | G83: =IF(ISNUMBER(E83),ROUND(D83-E83,2),"") -> 0.14 | H83: Verify source and adjust GL to bank amount; bank–GL variance $0.14
A84: 46192 | B84: CHEQUE 1066 | C84: CHQ#1066 | D84: -2934.68 | E84: =_xlfn.XLOOKUP(C84,gl_cash_extract_jun2026!D:D,gl_cash_extract_jun2026!E:E,"Not Found") -> -2934.68 | F84: =IF(E84="Not Found","Missing from GL",IF(D84=E84,"Matched","Difference")) -> Matched | G84: =IF(ISNUMBER(E84),ROUND(D84-E84,2),"") -> 0
A85: 46192 | B85: DEP BELL CDA AP REF40504 | C85: REF40504 | D85: 30144.87 | E85: =_xlfn.XLOOKUP(C85,gl_cash_extract_jun2026!D:D,gl_cash_extract_jun2026!E:E,"Not Found") -> 30144.87 | F85: =IF(E85="Not Found","Missing from GL",IF(D85=E85,"Matched","Difference")) -> Matched | G85: =IF(ISNUMBER(E85),ROUND(D85-E85,2),"") -> 0
A86: 46192 | B86: EFT BRANDT TRACTOR REF40408 | C86: REF40408 | D86: -17410.26 | E86: =_xlfn.XLOOKUP(C86,gl_cash_extract_jun2026!D:D,gl_cash_extract_jun2026!E:E,"Not Found") -> -17410.26 | F86: =IF(E86="Not Found","Missing from GL",IF(D86=E86,"Matched","Difference")) -> Matched | G86: =IF(ISNUMBER(E86),ROUND(D86-E86,2),"") -> 0
A87: 46192 | B87: EFT REGION HALTON PERMIT REF40270 | C87: REF40270 | D87: -10385.29 | E87: =_xlfn.XLOOKUP(C87,gl_cash_extract_jun2026!D:D,gl_cash_extract_jun2026!E:E,"Not Found") -> -10385.29 | F87: =IF(E87="Not Found","Missing from GL",IF(D87=E87,"Matched","Difference")) -> Matched | G87: =IF(ISNUMBER(E87),ROUND(D87-E87,2),"") -> 0
A88: 46192 | B88: EFT VERMEER CDA REF40547 | C88: REF40547 | D88: -14976.01 | E88: =_xlfn.XLOOKUP(C88,gl_cash_extract_jun2026!D:D,gl_cash_extract_jun2026!E:E,"Not Found") -> -14976.01 | F88: =IF(E88="Not Found","Missing from GL",IF(D88=E88,"Matched","Difference")) -> Matched | G88: =IF(ISNUMBER(E88),ROUND(D88-E88,2),"") -> 0
A89: 46195 | B89: CHEQUE 1059 | C89: CHQ#1059 | D89: -14341.45 | E89: =_xlfn.XLOOKUP(C89,gl_cash_extract_jun2026!D:D,gl_cash_extract_jun2026!E:E,"Not Found") -> -14341.45 | F89: =IF(E89="Not Found","Missing from GL",IF(D89=E89,"Matched","Difference")) -> Matched | G89: =IF(ISNUMBER(E89),ROUND(D89-E89,2),"") -> 0
A90: 46195 | B90: CHEQUE 1061 | C90: CHQ#1061 | D90: -13390.63 | E90: =_xlfn.XLOOKUP(C90,gl_cash_extract_jun2026!D:D,gl_cash_extract_jun2026!E:E,"Not Found") -> -13390.63 | F90: =IF(E90="Not Found","Missing from GL",IF(D90=E90,"Matched","Difference")) -> Matched | G90: =IF(ISNUMBER(E90),ROUND(D90-E90,2),"") -> 0
A91: 46195 | B91: CHEQUE 1078 | C91: CHQ#1078 | D91: -3495.61 | E91: =_xlfn.XLOOKUP(C91,gl_cash_extract_jun2026!D:D,gl_cash_extract_jun2026!E:E,"Not Found") -> -3495.61 | F91: =IF(E91="Not Found","Missing from GL",IF(D91=E91,"Matched","Difference")) -> Matched | G91: =IF(ISNUMBER(E91),ROUND(D91-E91,2),"") -> 0
A92: 46195 | B92: CHQ DITCH WITCH ONT REF40249 | C92: REF40249 | D92: -9603.95 | E92: =_xlfn.XLOOKUP(C92,gl_cash_extract_jun2026!D:D,gl_cash_extract_jun2026!E:E,"Not Found") -> -9603.95 | F92: =IF(E92="Not Found","Missing from GL",IF(D92=E92,"Matched","Difference")) -> Matched | G92: =IF(ISNUMBER(E92),ROUND(D92-E92,2),"") -> 0
A93: 46195 | B93: DEP COGECO CONNEXION REF40229 | C93: REF40229 | D93: 59150.99 | E93: =_xlfn.XLOOKUP(C93,gl_cash_extract_jun2026!D:D,gl_cash_extract_jun2026!E:E,"Not Found") -> 59150.99 | F93: =IF(E93="Not Found","Missing from GL",IF(D93=E93,"Matched","Difference")) -> Matched | G93: =IF(ISNUMBER(E93),ROUND(D93-E93,2),"") -> 0
A94: 46195 | B94: EFT ANIXTER CDA SUPPLY REF40901 | C94: REF40901 | D94: -9274.79 | E94: =_xlfn.XLOOKUP(C94,gl_cash_extract_jun2026!D:D,gl_cash_extract_jun2026!E:E,"Not Found") -> -9274.16 | F94: =IF(E94="Not Found","Missing from GL",IF(D94=E94,"Matched","Difference")) -> Difference | G94: =IF(ISNUMBER(E94),ROUND(D94-E94,2),"") -> -0.63 | H94: Verify source and adjust GL to bank amount; bank–GL variance -$0.63
A95: 46195 | B95: EFT WSIB ONT PREMIUM REF40608 | C95: REF40608 | D95: -18548.06 | E95: =_xlfn.XLOOKUP(C95,gl_cash_extract_jun2026!D:D,gl_cash_extract_jun2026!E:E,"Not Found") -> -18548.06 | F95: =IF(E95="Not Found","Missing from GL",IF(D95=E95,"Matched","Difference")) -> Matched | G95: =IF(ISNUMBER(E95),ROUND(D95-E95,2),"") -> 0
A96: 46195 | B96: MERCHANT PROCESSING FEE MONERIS | C96: MER-0622 | D96: -389.44 | E96: =_xlfn.XLOOKUP(C96,gl_cash_extract_jun2026!D:D,gl_cash_extract_jun2026!E:E,"Not Found") -> Not Found | F96: =IF(E96="Not Found","Missing from GL",IF(D96=E96,"Matched","Difference")) -> Missing from GL | G96: =IF(ISNUMBER(E96),ROUND(D96-E96,2),"") | H96: Post bank fee/charge to the GL
A97: 46195 | B97: PAD ENTERPRISE FLEET REF40181 | C97: REF40181 | D97: -19936.42 | E97: =_xlfn.XLOOKUP(C97,gl_cash_extract_jun2026!D:D,gl_cash_extract_jun2026!E:E,"Not Found") -> -19936.42 | F97: =IF(E97="Not Found","Missing from GL",IF(D97=E97,"Matched","Difference")) -> Matched | G97: =IF(ISNUMBER(E97),ROUND(D97-E97,2),"") -> 0
A98: 46195 | B98: PAD ENTERPRISE FLEET REF40801 | C98: REF40801 | D98: -12259.66 | E98: =_xlfn.XLOOKUP(C98,gl_cash_extract_jun2026!D:D,gl_cash_extract_jun2026!E:E,"Not Found") -> -12259.66 | F98: =IF(E98="Not Found","Missing from GL",IF(D98=E98,"Matched","Difference")) -> Matched | G98: =IF(ISNUMBER(E98),ROUND(D98-E98,2),"") -> 0
A99: 46195 | B99: PAD INTACT INSURANCE PREM REF40884 | C99: REF40884 | D99: -1887.08 | E99: =_xlfn.XLOOKUP(C99,gl_cash_extract_jun2026!D:D,gl_cash_extract_jun2026!E:E,"Not Found") -> -1887.53 | F99: =IF(E99="Not Found","Missing from GL",IF(D99=E99,"Matched","Difference")) -> Difference | G99: =IF(ISNUMBER(E99),ROUND(D99-E99,2),"") -> 0.45 | H99: Verify source and adjust GL to bank amount; bank–GL variance $0.45
A100: 46195 | B100: PAD UNITED RENTALS INC REF40865 | C100: REF40865 | D100: -6649.18 | E100: =_xlfn.XLOOKUP(C100,gl_cash_extract_jun2026!D:D,gl_cash_extract_jun2026!E:E,"Not Found") -> -6648.91 | F100: =IF(E100="Not Found","Missing from GL",IF(D100=E100,"Matched","Difference")) -> Difference | G100: =IF(ISNUMBER(E100),ROUND(D100-E100,2),"") -> -0.27 | H100: Verify source and adjust GL to bank amount; bank–GL variance -$0.27
A101: 46196 | B101: EFT TELECON DESIGN REF40618 | C101: REF40618 | D101: -22691.11 | E101: =_xlfn.XLOOKUP(C101,gl_cash_extract_jun2026!D:D,gl_cash_extract_jun2026!E:E,"Not Found") -> -22691.11 | F101: =IF(E101="Not Found","Missing from GL",IF(D101=E101,"Matched","Difference")) -> Matched | G101: =IF(ISNUMBER(E101),ROUND(D101-E101,2),"") -> 0
A102: 46197 | B102: ADP PAYROLL PPD REF40752 | C102: REF40752 | D102: -10531.31 | E102: =_xlfn.XLOOKUP(C102,gl_cash_extract_jun2026!D:D,gl_cash_extract_jun2026!E:E,"Not Found") -> -10531.31 | F102: =IF(E102="Not Found","Missing from GL",IF(D102=E102,"Matched","Difference")) -> Matched | G102: =IF(ISNUMBER(E102),ROUND(D102-E102,2),"") -> 0
A103: 46197 | B103: CHEQUE 1075 | C103: CHQ#1075 | D103: -7694.16 | E103: =_xlfn.XLOOKUP(C103,gl_cash_extract_jun2026!D:D,gl_cash_extract_jun2026!E:E,"Not Found") -> -7694.16 | F103: =IF(E103="Not Found","Missing from GL",IF(D103=E103,"Matched","Difference")) -> Matched | G103: =IF(ISNUMBER(E103),ROUND(D103-E103,2),"") -> 0
A104: 46197 | B104: DEP ROGERS COMM AP REF40425 | C104: REF40425 | D104: 30455.14 | E104: =_xlfn.XLOOKUP(C104,gl_cash_extract_jun2026!D:D,gl_cash_extract_jun2026!E:E,"Not Found") -> 30455.14 | F104: =IF(E104="Not Found","Missing from GL",IF(D104=E104,"Matched","Difference")) -> Matched | G104: =IF(ISNUMBER(E104),ROUND(D104-E104,2),"") -> 0
A105: 46197 | B105: EFT BELL CDA PAYMENT REF40314 | C105: REF40314 | D105: -22899.9 | E105: =_xlfn.XLOOKUP(C105,gl_cash_extract_jun2026!D:D,gl_cash_extract_jun2026!E:E,"Not Found") -> -22899.9 | F105: =IF(E105="Not Found","Missing from GL",IF(D105=E105,"Matched","Difference")) -> Matched | G105: =IF(ISNUMBER(E105),ROUND(D105-E105,2),"") -> 0
A106: 46197 | B106: EFT WESCO DIST CANADA REF40852 | C106: REF40852 | D106: -13902.08 | E106: =_xlfn.XLOOKUP(C106,gl_cash_extract_jun2026!D:D,gl_cash_extract_jun2026!E:E,"Not Found") -> -13902.44 | F106: =IF(E106="Not Found","Missing from GL",IF(D106=E106,"Matched","Difference")) -> Difference | G106: =IF(ISNUMBER(E106),ROUND(D106-E106,2),"") -> 0.36 | H106: Verify source and adjust GL to bank amount; bank–GL variance $0.36
A107: 46197 | B107: PAD MILTON HYDRO REF40780 | C107: REF40780 | D107: -16540.94 | E107: =_xlfn.XLOOKUP(C107,gl_cash_extract_jun2026!D:D,gl_cash_extract_jun2026!E:E,"Not Found") -> -16540.94 | F107: =IF(E107="Not Found","Missing from GL",IF(D107=E107,"Matched","Difference")) -> Matched | G107: =IF(ISNUMBER(E107),ROUND(D107-E107,2),"") -> 0
A108: 46198 | B108: CHEQUE 1045 | C108: CHQ#1045 | D108: -20256.73 | E108: =_xlfn.XLOOKUP(C108,gl_cash_extract_jun2026!D:D,gl_cash_extract_jun2026!E:E,"Not Found") -> -20256.73 | F108: =IF(E108="Not Found","Missing from GL",IF(D108=E108,"Matched","Difference")) -> Matched | G108: =IF(ISNUMBER(E108),ROUND(D108-E108,2),"") -> 0
A109: 46198 | B109: CHEQUE 1069 | C109: CHQ#1069 | D109: -7966.03 | E109: =_xlfn.XLOOKUP(C109,gl_cash_extract_jun2026!D:D,gl_cash_extract_jun2026!E:E,"Not Found") -> -7966.03 | F109: =IF(E109="Not Found","Missing from GL",IF(D109=E109,"Matched","Difference")) -> Matched | G109: =IF(ISNUMBER(E109),ROUND(D109-E109,2),"") -> 0
A110: 46198 | B110: CHQ DITCH WITCH ONT REF40348 | C110: REF40348 | D110: -19617.67 | E110: =_xlfn.XLOOKUP(C110,gl_cash_extract_jun2026!D:D,gl_cash_extract_jun2026!E:E,"Not Found") -> -19617.67 | F110: =IF(E110="Not Found","Missing from GL",IF(D110=E110,"Matched","Difference")) -> Matched | G110: =IF(ISNUMBER(E110),ROUND(D110-E110,2),"") -> 0
A111: 46198 | B111: EFT BRANDT TRACTOR REF40163 | C111: REF40163 | D111: -5308.77 | E111: =_xlfn.XLOOKUP(C111,gl_cash_extract_jun2026!D:D,gl_cash_extract_jun2026!E:E,"Not Found") -> -5308.77 | F111: =IF(E111="Not Found","Missing from GL",IF(D111=E111,"Matched","Difference")) -> Matched | G111: =IF(ISNUMBER(E111),ROUND(D111-E111,2),"") -> 0
A112: 46198 | B112: EFT VERMEER CDA REF40542 | C112: REF40542 | D112: -7711.34 | E112: =_xlfn.XLOOKUP(C112,gl_cash_extract_jun2026!D:D,gl_cash_extract_jun2026!E:E,"Not Found") -> -7711.34 | F112: =IF(E112="Not Found","Missing from GL",IF(D112=E112,"Matched","Difference")) -> Matched | G112: =IF(ISNUMBER(E112),ROUND(D112-E112,2),"") -> 0
A113: 46198 | B113: PRE-AUTH DEBIT UNKNOWN ORIG 7719 | C113: PAD-7719 | D113: -1260 | E113: =_xlfn.XLOOKUP(C113,gl_cash_extract_jun2026!D:D,gl_cash_extract_jun2026!E:E,"Not Found") -> Not Found | F113: =IF(E113="Not Found","Missing from GL",IF(D113=E113,"Matched","Difference")) -> Missing from GL | G113: =IF(ISNUMBER(E113),ROUND(D113-E113,2),"") | H113: Investigate the bank-only transaction and post if valid
A114: 46199 | B114: E-TRANSFER RECEIVED T4X99A | C114: ETR-T4X99A | D114: 2150 | E114: =_xlfn.XLOOKUP(C114,gl_cash_extract_jun2026!D:D,gl_cash_extract_jun2026!E:E,"Not Found") -> Not Found | F114: =IF(E114="Not Found","Missing from GL",IF(D114=E114,"Matched","Difference")) -> Missing from GL | G114: =IF(ISNUMBER(E114),ROUND(D114-E114,2),"") | H114: Post bank fee/charge to the GL
A115: 46199 | B115: EFT BRANDT TRACTOR REF40281 | C115: REF40281 | D115: -15125.76 | E115: =_xlfn.XLOOKUP(C115,gl_cash_extract_jun2026!D:D,gl_cash_extract_jun2026!E:E,"Not Found") -> -15125.76 | F115: =IF(E115="Not Found","Missing from GL",IF(D115=E115,"Matched","Difference")) -> Matched | G115: =IF(ISNUMBER(E115),ROUND(D115-E115,2),"") -> 0
A116: 46199 | B116: EFT VERMEER CDA REF40716 | C116: REF40716 | D116: -8508.86 | E116: =_xlfn.XLOOKUP(C116,gl_cash_extract_jun2026!D:D,gl_cash_extract_jun2026!E:E,"Not Found") -> -8508.86 | F116: =IF(E116="Not Found","Missing from GL",IF(D116=E116,"Matched","Difference")) -> Matched | G116: =IF(ISNUMBER(E116),ROUND(D116-E116,2),"") -> 0
A117: 46199 | B117: PAD PETROCAN SUPERPASS REF40482 | C117: REF40482 | D117: -22249.66 | E117: =_xlfn.XLOOKUP(C117,gl_cash_extract_jun2026!D:D,gl_cash_extract_jun2026!E:E,"Not Found") -> -22249.66 | F117: =IF(E117="Not Found","Missing from GL",IF(D117=E117,"Matched","Difference")) -> Matched | G117: =IF(ISNUMBER(E117),ROUND(D117-E117,2),"") -> 0
A118: 46199 | B118: PAD SHELL FLEET REF40675 | C118: REF40675 | D118: -20774.91 | E118: =_xlfn.XLOOKUP(C118,gl_cash_extract_jun2026!D:D,gl_cash_extract_jun2026!E:E,"Not Found") -> -20774.91 | F118: =IF(E118="Not Found","Missing from GL",IF(D118=E118,"Matched","Difference")) -> Matched | G118: =IF(ISNUMBER(E118),ROUND(D118-E118,2),"") -> 0
A119: 46199 | B119: PAD SHELL FLEET REF40706 | C119: REF40706 | D119: -6535.31 | E119: =_xlfn.XLOOKUP(C119,gl_cash_extract_jun2026!D:D,gl_cash_extract_jun2026!E:E,"Not Found") -> -6535.31 | F119: =IF(E119="Not Found","Missing from GL",IF(D119=E119,"Matched","Difference")) -> Matched | G119: =IF(ISNUMBER(E119),ROUND(D119-E119,2),"") -> 0
A120: 46199 | B120: PAD UNITED RENTALS REF40341 | C120: REF40341 | D120: -22311.13 | E120: =_xlfn.XLOOKUP(C120,gl_cash_extract_jun2026!D:D,gl_cash_extract_jun2026!E:E,"Not Found") -> -22311.13 | F120: =IF(E120="Not Found","Missing from GL",IF(D120=E120,"Matched","Difference")) -> Matched | G120: =IF(ISNUMBER(E120),ROUND(D120-E120,2),"") -> 0
A121: 46203 | B121: INTEREST EARNED | C121: INT-JUN | D121: 214.87 | E121: =_xlfn.XLOOKUP(C121,gl_cash_extract_jun2026!D:D,gl_cash_extract_jun2026!E:E,"Not Found") -> Not Found | F121: =IF(E121="Not Found","Missing from GL",IF(D121=E121,"Matched","Difference")) -> Missing from GL | G121: =IF(ISNUMBER(E121),ROUND(D121-E121,2),"") | H121: Post bank interest income to the GL
A122: 46203 | B122: MONTHLY ACCOUNT FEE | C122: SVC-JUN | D122: -125 | E122: =_xlfn.XLOOKUP(C122,gl_cash_extract_jun2026!D:D,gl_cash_extract_jun2026!E:E,"Not Found") -> Not Found | F122: =IF(E122="Not Found","Missing from GL",IF(D122=E122,"Matched","Difference")) -> Missing from GL | G122: =IF(ISNUMBER(E122),ROUND(D122-E122,2),"") | H122: Post bank fee/charge to the GL
A123: 46203 | B123: SERVICE CHARGE - WIRE PAYMENT | C123: WIRE-FEE | D123: -45 | E123: =_xlfn.XLOOKUP(C123,gl_cash_extract_jun2026!D:D,gl_cash_extract_jun2026!E:E,"Not Found") -> Not Found | F123: =IF(E123="Not Found","Missing from GL",IF(D123=E123,"Matched","Difference")) -> Missing from GL | G123: =IF(ISNUMBER(E123),ROUND(D123-E123,2),"") | H123: Post bank fee/charge to the GL
C125: Full Bank Activity Total | D125: =SUM(Bankl[Amount]) -> 222907.3 | F125: Net Amount Difference | G125: =SUM(Bankl[Difference]) -> -0.35

Sheet gl_cash_extract_jun2026
A1: Date | B1: Account | C1: Memo | D1: DocNo | E1: Amount | F1: Bank Match | G1: Reconciliation Status | H1: Difference Amount | I1: Action / Notes
A2: 46174 | B2: 1010 Cash — Operating | C2: Milton Hydro — invoice payment | D2: CHQ#1064 | E2: -8067.99 | F2: =_xlfn.XLOOKUP(Cash[[#This Row],[DocNo]],bank_statement_jun2026!C:C,bank_statement_jun2026!D:D,"Not Found") -> -8067.99 | G2: =IF(F2="Not Found","Missing from Bank",IF(ROUND(E2,2)=ROUND(F2,2),"Matched","Difference")) -> Matched | H2: =IF(ISNUMBER(F2),ROUND(E2-F2,2),"") -> 0
A3: 46174 | B3: 1010 Cash — Operating | C3: Region of Halton — invoice payment | D3: CHQ#1042 | E3: -10230.18 | F3: =_xlfn.XLOOKUP(Cash[[#This Row],[DocNo]],bank_statement_jun2026!C:C,bank_statement_jun2026!D:D,"Not Found") -> -10230.18 | G3: =IF(F3="Not Found","Missing from Bank",IF(ROUND(E3,2)=ROUND(F3,2),"Matched","Difference")) -> Matched | H3: =IF(ISNUMBER(F3),ROUND(E3-F3,2),"") -> 0
A4: 46174 | B4: 1010 Cash — Operating | C4: Rogers Communications — progress billing | D4: REF40771 | E4: 88790.68 | F4: =_xlfn.XLOOKUP(Cash[[#This Row],[DocNo]],bank_statement_jun2026!C:C,bank_statement_jun2026!D:D,"Not Found") -> 88790.68 | G4: =IF(F4="Not Found","Missing from Bank",IF(ROUND(E4,2)=ROUND(F4,2),"Matched","Difference")) -> Matched | H4: =IF(ISNUMBER(F4),ROUND(E4-F4,2),"") -> 0
A5: 46174 | B5: 1010 Cash — Operating | C5: Shell Fleet Card — invoice payment | D5: REF40144 | E5: -12217.56 | F5: =_xlfn.XLOOKUP(Cash[[#This Row],[DocNo]],bank_statement_jun2026!C:C,bank_statement_jun2026!D:D,"Not Found") -> -12217.56 | G5: =IF(F5="Not Found","Missing from Bank",IF(ROUND(E5,2)=ROUND(F5,2),"Matched","Difference")) -> Matched | H5: =IF(ISNUMBER(F5),ROUND(E5-F5,2),"") -> 0
A6: 46175 | B6: 1010 Cash — Operating | C6: Enterprise Fleet Mgmt — invoice payment | D6: REF40486 | E6: -5365.64 | F6: =_xlfn.XLOOKUP(Cash[[#This Row],[DocNo]],bank_statement_jun2026!C:C,bank_statement_jun2026!D:D,"Not Found") -> -5365.64 | G6: =IF(F6="Not Found","Missing from Bank",IF(ROUND(E6,2)=ROUND(F6,2),"Matched","Difference")) -> Matched | H6: =IF(ISNUMBER(F6),ROUND(E6-F6,2),"") -> 0
A7: 46175 | B7: 1010 Cash — Operating | C7: Telecon Design — invoice payment | D7: CHQ#1051 | E7: -17040.77 | F7: =_xlfn.XLOOKUP(Cash[[#This Row],[DocNo]],bank_statement_jun2026!C:C,bank_statement_jun2026!D:D,"Not Found") -> -17040.77 | G7: =IF(F7="Not Found","Missing from Bank",IF(ROUND(E7,2)=ROUND(F7,2),"Matched","Difference")) -> Matched | H7: =IF(ISNUMBER(F7),ROUND(E7-F7,2),"") -> 0
A8: 46175 | B8: 1010 Cash — Operating | C8: Telus network build — milestone | D8: REF40191 | E8: 88411.47 | F8: =_xlfn.XLOOKUP(Cash[[#This Row],[DocNo]],bank_statement_jun2026!C:C,bank_statement_jun2026!D:D,"Not Found") -> 88411.47 | G8: =IF(F8="Not Found","Missing from Bank",IF(ROUND(E8,2)=ROUND(F8,2),"Matched","Difference")) -> Matched | H8: =IF(ISNUMBER(F8),ROUND(E8-F8,2),"") -> 0
A9: 46176 | B9: 1010 Cash — Operating | C9: Brandt Tractor Ltd — invoice payment | D9: REF40276 | E9: -12316.92 | F9: =_xlfn.XLOOKUP(Cash[[#This Row],[DocNo]],bank_statement_jun2026!C:C,bank_statement_jun2026!D:D,"Not Found") -> -12316.92 | G9: =IF(F9="Not Found","Missing from Bank",IF(ROUND(E9,2)=ROUND(F9,2),"Matched","Difference")) -> Matched | H9: =IF(ISNUMBER(F9),ROUND(E9-F9,2),"") -> 0
A10: 46176 | B10: 1010 Cash — Operating | C10: Milton Hydro — invoice payment | D10: REF40442 | E10: -20094.18 | F10: =_xlfn.XLOOKUP(Cash[[#This Row],[DocNo]],bank_statement_jun2026!C:C,bank_statement_jun2026!D:D,"Not Found") -> -20094.18 | G10: =IF(F10="Not Found","Missing from Bank",IF(ROUND(E10,2)=ROUND(F10,2),"Matched","Difference")) -> Matched | H10: =IF(ISNUMBER(F10),ROUND(E10-F10,2),"") -> 0
A11: 46176 | B11: 1010 Cash — Operating | C11: Rogers Communications — progress billing | D11: REF40398 | E11: 102367.19 | F11: =_xlfn.XLOOKUP(Cash[[#This Row],[DocNo]],bank_statement_jun2026!C:C,bank_statement_jun2026!D:D,"Not Found") -> 102367.19 | G11: =IF(F11="Not Found","Missing from Bank",IF(ROUND(E11,2)=ROUND(F11,2),"Matched","Difference")) -> Matched | H11: =IF(ISNUMBER(F11),ROUND(E11-F11,2),"") -> 0
A12: 46176 | B12: 1010 Cash — Operating | C12: Shell Fleet Card — invoice payment | D12: CHQ#1048 | E12: -21094.19 | F12: =_xlfn.XLOOKUP(Cash[[#This Row],[DocNo]],bank_statement_jun2026!C:C,bank_statement_jun2026!D:D,"Not Found") -> -21094.19 | G12: =IF(F12="Not Found","Missing from Bank",IF(ROUND(E12,2)=ROUND(F12,2),"Matched","Difference")) -> Matched | H12: =IF(ISNUMBER(F12),ROUND(E12-F12,2),"") -> 0
A13: 46177 | B13: 1010 Cash — Operating | C13: Bell Canada — invoice payment | D13: REF40826 | E13: -4183.67 | F13: =_xlfn.XLOOKUP(Cash[[#This Row],[DocNo]],bank_statement_jun2026!C:C,bank_statement_jun2026!D:D,"Not Found") -> -4183.58 | G13: =IF(F13="Not Found","Missing from Bank",IF(ROUND(E13,2)=ROUND(F13,2),"Matched","Difference")) -> Difference | H13: =IF(ISNUMBER(F13),ROUND(E13-F13,2),"") -> -0.09 | I13: Verify source and adjust GL to bank amount; GL–bank variance -$0.09
A14: 46177 | B14: 1010 Cash — Operating | C14: Brandt Tractor Ltd — invoice payment | D14: REF40587 | E14: -6479.58 | F14: =_xlfn.XLOOKUP(Cash[[#This Row],[DocNo]],bank_statement_jun2026!C:C,bank_statement_jun2026!D:D,"Not Found") -> -6479.58 | G14: =IF(F14="Not Found","Missing from Bank",IF(ROUND(E14,2)=ROUND(F14,2),"Matched","Difference")) -> Matched | H14: =IF(ISNUMBER(F14),ROUND(E14-F14,2),"") -> 0
A15: 46177 | B15: 1010 Cash — Operating | C15: Shell Fleet Card — invoice payment | D15: REF40128 | E15: -3503.79 | F15: =_xlfn.XLOOKUP(Cash[[#This Row],[DocNo]],bank_statement_jun2026!C:C,bank_statement_jun2026!D:D,"Not Found") -> -3503.79 | G15: =IF(F15="Not Found","Missing from Bank",IF(ROUND(E15,2)=ROUND(F15,2),"Matched","Difference")) -> Matched | H15: =IF(ISNUMBER(F15),ROUND(E15-F15,2),"") -> 0
A16: 46177 | B16: 1010 Cash — Operating | C16: WESCO Distribution — invoice payment | D16: REF40326 | E16: -12272.98 | F16: =_xlfn.XLOOKUP(Cash[[#This Row],[DocNo]],bank_statement_jun2026!C:C,bank_statement_jun2026!D:D,"Not Found") -> -12272.98 | G16: =IF(F16="Not Found","Missing from Bank",IF(ROUND(E16,2)=ROUND(F16,2),"Matched","Difference")) -> Matched | H16: =IF(ISNUMBER(F16),ROUND(E16-F16,2),"") -> 0
A17: 46178 | B17: 1010 Cash — Operating | C17: Bell Canada — invoice payment | D17: CHQ#1077 | E17: -16110.81 | F17: =_xlfn.XLOOKUP(Cash[[#This Row],[DocNo]],bank_statement_jun2026!C:C,bank_statement_jun2026!D:D,"Not Found") -> -16110.81 | G17: =IF(F17="Not Found","Missing from Bank",IF(ROUND(E17,2)=ROUND(F17,2),"Matched","Difference")) -> Matched | H17: =IF(ISNUMBER(F17),ROUND(E17-F17,2),"") -> 0
A18: 46178 | B18: 1010 Cash — Operating | C18: Bell aerial build — holdback release | D18: REF40634 | E18: 77425.86 | F18: =_xlfn.XLOOKUP(Cash[[#This Row],[DocNo]],bank_statement_jun2026!C:C,bank_statement_jun2026!D:D,"Not Found") -> 77425.86 | G18: =IF(F18="Not Found","Missing from Bank",IF(ROUND(E18,2)=ROUND(F18,2),"Matched","Difference")) -> Matched | H18: =IF(ISNUMBER(F18),ROUND(E18-F18,2),"") -> 0
A19: 46178 | B19: 1010 Cash — Operating | C19: GFL Environmental — invoice payment | D19: REF40334 | E19: -14685.67 | F19: =_xlfn.XLOOKUP(Cash[[#This Row],[DocNo]],bank_statement_jun2026!C:C,bank_statement_jun2026!D:D,"Not Found") -> -14685.67 | G19: =IF(F19="Not Found","Missing from Bank",IF(ROUND(E19,2)=ROUND(F19,2),"Matched","Difference")) -> Matched | H19: =IF(ISNUMBER(F19),ROUND(E19-F19,2),"") -> 0
A20: 46178 | B20: 1010 Cash — Operating | C20: Shell Fleet Card — invoice payment | D20: REF40539 | E20: -6506.94 | F20: =_xlfn.XLOOKUP(Cash[[#This Row],[DocNo]],bank_statement_jun2026!C:C,bank_statement_jun2026!D:D,"Not Found") -> -6506.94 | G20: =IF(F20="Not Found","Missing from Bank",IF(ROUND(E20,2)=ROUND(F20,2),"Matched","Difference")) -> Matched | H20: =IF(ISNUMBER(F20),ROUND(E20-F20,2),"") -> 0
A21: 46181 | B21: 1010 Cash — Operating | C21: Bell Canada — invoice payment | D21: REF40379 | E21: -14193.51 | F21: =_xlfn.XLOOKUP(Cash[[#This Row],[DocNo]],bank_statement_jun2026!C:C,bank_statement_jun2026!D:D,"Not Found") -> -14193.51 | G21: =IF(F21="Not Found","Missing from Bank",IF(ROUND(E21,2)=ROUND(F21,2),"Matched","Difference")) -> Matched | H21: =IF(ISNUMBER(F21),ROUND(E21-F21,2),"") -> 0
A22: 46181 | B22: 1010 Cash — Operating | C22: Bell aerial build — holdback release | D22: REF40527 | E22: 109123.56 | F22: =_xlfn.XLOOKUP(Cash[[#This Row],[DocNo]],bank_statement_jun2026!C:C,bank_statement_jun2026!D:D,"Not Found") -> 109123.56 | G22: =IF(F22="Not Found","Missing from Bank",IF(ROUND(E22,2)=ROUND(F22,2),"Matched","Difference")) -> Matched | H22: =IF(ISNUMBER(F22),ROUND(E22-F22,2),"") -> 0
A23: 46181 | B23: 1010 Cash — Operating | C23: Bell aerial build — holdback release | D23: REF40561 | E23: 104277.78 | F23: =_xlfn.XLOOKUP(Cash[[#This Row],[DocNo]],bank_statement_jun2026!C:C,bank_statement_jun2026!D:D,"Not Found") -> 104277.78 | G23: =IF(F23="Not Found","Missing from Bank",IF(ROUND(E23,2)=ROUND(F23,2),"Matched","Difference")) -> Matched | H23: =IF(ISNUMBER(F23),ROUND(E23-F23,2),"") -> 0
A24: 46181 | B24: 1010 Cash — Operating | C24: Ditch Witch of Ontario — invoice payment | D24: CHQ#1053 | E24: -19414.58 | F24: =_xlfn.XLOOKUP(Cash[[#This Row],[DocNo]],bank_statement_jun2026!C:C,bank_statement_jun2026!D:D,"Not Found") -> -19414.58 | G24: =IF(F24="Not Found","Missing from Bank",IF(ROUND(E24,2)=ROUND(F24,2),"Matched","Difference")) -> Matched | H24: =IF(ISNUMBER(F24),ROUND(E24-F24,2),"") -> 0
A25: 46181 | B25: 1010 Cash — Operating | C25: Enterprise Fleet Mgmt — invoice payment | D25: REF40206 | E25: -23647.98 | F25: =_xlfn.XLOOKUP(Cash[[#This Row],[DocNo]],bank_statement_jun2026!C:C,bank_statement_jun2026!D:D,"Not Found") -> -23647.98 | G25: =IF(F25="Not Found","Missing from Bank",IF(ROUND(E25,2)=ROUND(F25,2),"Matched","Difference")) -> Matched | H25: =IF(ISNUMBER(F25),ROUND(E25-F25,2),"") -> 0
... A54: 46185 | B54: 1010 Cash — Operating | C54: Enterprise Fleet Mgmt — invoice payment | D54: REF40376 | E54: -16179.58 | F54: =_xlfn.XLOOKUP(Cash[[#This Row],[DocNo]],bank_statement_jun2026!C:C,bank_statement_jun2026!D:D,"Not Found") -> -16179.58 | G54: =IF(F54="Not Found","Missing from Bank",IF(ROUND(E54,2)=ROUND(F54,2),"Matched","Difference")) -> Matched | H54: =IF(ISNUMBER(F54),ROUND(E54-F54,2),"") -> 0
A55: 46185 | B55: 1010 Cash — Operating | C55: GFL Environmental — invoice payment | D55: REF40929 | E55: -743.29 | F55: =_xlfn.XLOOKUP(Cash[[#This Row],[DocNo]],bank_statement_jun2026!C:C,bank_statement_jun2026!D:D,"Not Found") -> -743.6 | G55: =IF(F55="Not Found","Missing from Bank",IF(ROUND(E55,2)=ROUND(F55,2),"Matched","Difference")) -> Difference | H55: =IF(ISNUMBER(F55),ROUND(E55-F55,2),"") -> 0.31 | I55: Verify source and adjust GL to bank amount; GL–bank variance $0.31
A56: 46185 | B56: 1010 Cash — Operating | C56: Petro-Canada SuperPass — invoice payment | D56: CHQ#1044 | E56: -10980.23 | F56: =_xlfn.XLOOKUP(Cash[[#This Row],[DocNo]],bank_statement_jun2026!C:C,bank_statement_jun2026!D:D,"Not Found") -> -10980.23 | G56: =IF(F56="Not Found","Missing from Bank",IF(ROUND(E56,2)=ROUND(F56,2),"Matched","Difference")) -> Matched | H56: =IF(ISNUMBER(F56),ROUND(E56-F56,2),"") -> 0
A57: 46185 | B57: 1010 Cash — Operating | C57: Staples Business — invoice payment | D57: REF40167 | E57: -2483.78 | F57: =_xlfn.XLOOKUP(Cash[[#This Row],[DocNo]],bank_statement_jun2026!C:C,bank_statement_jun2026!D:D,"Not Found") -> -2483.78 | G57: =IF(F57="Not Found","Missing from Bank",IF(ROUND(E57,2)=ROUND(F57,2),"Matched","Difference")) -> Matched | H57: =IF(ISNUMBER(F57),ROUND(E57-F57,2),"") -> 0
A58: 46188 | B58: 1010 Cash — Operating | C58: Bell Canada — invoice payment | D58: REF40721 | E58: -15901.99 | F58: =_xlfn.XLOOKUP(Cash[[#This Row],[DocNo]],bank_statement_jun2026!C:C,bank_statement_jun2026!D:D,"Not Found") -> -15901.99 | G58: =IF(F58="Not Found","Missing from Bank",IF(ROUND(E58,2)=ROUND(F58,2),"Matched","Difference")) -> Matched | H58: =IF(ISNUMBER(F58),ROUND(E58-F58,2),"") -> 0
A59: 46188 | B59: 1010 Cash — Operating | C59: Home Depot Pro — invoice payment | D59: REF40412 | E59: -8619.37 | F59: =_xlfn.XLOOKUP(Cash[[#This Row],[DocNo]],bank_statement_jun2026!C:C,bank_statement_jun2026!D:D,"Not Found") -> -8619.37 | G59: =IF(F59="Not Found","Missing from Bank",IF(ROUND(E59,2)=ROUND(F59,2),"Matched","Difference")) -> Matched | H59: =IF(ISNUMBER(F59),ROUND(E59-F59,2),"") -> 0
A60: 46188 | B60: 1010 Cash — Operating | C60: Home Depot Pro — invoice payment | D60: CHQ#1054 | E60: -4550.69 | F60: =_xlfn.XLOOKUP(Cash[[#This Row],[DocNo]],bank_statement_jun2026!C:C,bank_statement_jun2026!D:D,"Not Found") -> -4550.69 | G60: =IF(F60="Not Found","Missing from Bank",IF(ROUND(E60,2)=ROUND(F60,2),"Matched","Difference")) -> Matched | H60: =IF(ISNUMBER(F60),ROUND(E60-F60,2),"") -> 0
A61: 46188 | B61: 1010 Cash — Operating | C61: Milton Hydro — invoice payment | D61: REF40659 | E61: -21240.09 | F61: =_xlfn.XLOOKUP(Cash[[#This Row],[DocNo]],bank_statement_jun2026!C:C,bank_statement_jun2026!D:D,"Not Found") -> -21240.09 | G61: =IF(F61="Not Found","Missing from Bank",IF(ROUND(E61,2)=ROUND(F61,2),"Matched","Difference")) -> Matched | H61: =IF(ISNUMBER(F61),ROUND(E61-F61,2),"") -> 0
A62: 46188 | B62: 1010 Cash — Operating | C62: Rogers Communications — invoice payment | D62: REF40238 | E62: -19356.19 | F62: =_xlfn.XLOOKUP(Cash[[#This Row],[DocNo]],bank_statement_jun2026!C:C,bank_statement_jun2026!D:D,"Not Found") -> -19356.19 | G62: =IF(F62="Not Found","Missing from Bank",IF(ROUND(E62,2)=ROUND(F62,2),"Matched","Difference")) -> Matched | H62: =IF(ISNUMBER(F62),ROUND(E62-F62,2),"") -> 0
A63: 46188 | B63: 1010 Cash — Operating | C63: Staples Business — invoice payment | D63: REF40284 | E63: -9270.17 | F63: =_xlfn.XLOOKUP(Cash[[#This Row],[DocNo]],bank_statement_jun2026!C:C,bank_statement_jun2026!D:D,"Not Found") -> -9270.17 | G63: =IF(F63="Not Found","Missing from Bank",IF(ROUND(E63,2)=ROUND(F63,2),"Matched","Difference")) -> Matched | H63: =IF(ISNUMBER(F63),ROUND(E63-F63,2),"") -> 0
A64: 46188 | B64: 1010 Cash — Operating | C64: Vermeer Canada — invoice payment | D64: CHQ#1043 | E64: -12952.95 | F64: =_xlfn.XLOOKUP(Cash[[#This Row],[DocNo]],bank_statement_jun2026!C:C,bank_statement_jun2026!D:D,"Not Found") -> -12952.95 | G64: =IF(F64="Not Found","Missing from Bank",IF(ROUND(E64,2)=ROUND(F64,2),"Matched","Difference")) -> Matched | H64: =IF(ISNUMBER(F64),ROUND(E64-F64,2),"") -> 0
A65: 46188 | B65: 1010 Cash — Operating | C65: Vermeer Canada — invoice payment | D65: REF40614 | E65: -13321.03 | F65: =_xlfn.XLOOKUP(Cash[[#This Row],[DocNo]],bank_statement_jun2026!C:C,bank_statement_jun2026!D:D,"Not Found") -> -13321.03 | G65: =IF(F65="Not Found","Missing from Bank",IF(ROUND(E65,2)=ROUND(F65,2),"Matched","Difference")) -> Matched | H65: =IF(ISNUMBER(F65),ROUND(E65-F65,2),"") -> 0
A66: 46188 | B66: 1010 Cash — Operating | C66: WSIB Ontario — invoice payment | D66: CHQ#1047 | E66: -2837.17 | F66: =_xlfn.XLOOKUP(Cash[[#This Row],[DocNo]],bank_statement_jun2026!C:C,bank_statement_jun2026!D:D,"Not Found") -> -2837.17 | G66: =IF(F66="Not Found","Missing from Bank",IF(ROUND(E66,2)=ROUND(F66,2),"Matched","Difference")) -> Matched | H66: =IF(ISNUMBER(F66),ROUND(E66-F66,2),"") -> 0
A67: 46189 | B67: 1010 Cash — Operating | C67: Milton Hydro — invoice payment | D67: CHQ#1056 | E67: -15945.77 | F67: =_xlfn.XLOOKUP(Cash[[#This Row],[DocNo]],bank_statement_jun2026!C:C,bank_statement_jun2026!D:D,"Not Found") -> -15945.77 | G67: =IF(F67="Not Found","Missing from Bank",IF(ROUND(E67,2)=ROUND(F67,2),"Matched","Difference")) -> Matched | H67: =IF(ISNUMBER(F67),ROUND(E67-F67,2),"") -> 0
... A79: 46191 | B79: 1010 Cash — Operating | C79: Shell Fleet Card — invoice payment | D79: CHQ#1078 | E79: -3495.61 | F79: =_xlfn.XLOOKUP(Cash[[#This Row],[DocNo]],bank_statement_jun2026!C:C,bank_statement_jun2026!D:D,"Not Found") -> -3495.61 | G79: =IF(F79="Not Found","Missing from Bank",IF(ROUND(E79,2)=ROUND(F79,2),"Matched","Difference")) -> Matched | H79: =IF(ISNUMBER(F79),ROUND(E79-F79,2),"") -> 0
A80: 46191 | B80: 1010 Cash — Operating | C80: Shell Fleet Card — invoice payment | D80: REF40833 | E80: -2411.28 | F80: =_xlfn.XLOOKUP(Cash[[#This Row],[DocNo]],bank_statement_jun2026!C:C,bank_statement_jun2026!D:D,"Not Found") -> -2411.46 | G80: =IF(F80="Not Found","Missing from Bank",IF(ROUND(E80,2)=ROUND(F80,2),"Matched","Difference")) -> Difference | H80: =IF(ISNUMBER(F80),ROUND(E80-F80,2),"") -> 0.18 | I80: Verify source and adjust GL to bank amount; GL–bank variance $0.18
A81: 46191 | B81: 1010 Cash — Operating | C81: Telecon Design — invoice payment | D81: CHQ#1055 | E81: -10735.37 | F81: =_xlfn.XLOOKUP(Cash[[#This Row],[DocNo]],bank_statement_jun2026!C:C,bank_statement_jun2026!D:D,"Not Found") -> -10735.37 | G81: =IF(F81="Not Found","Missing from Bank",IF(ROUND(E81,2)=ROUND(F81,2),"Matched","Difference")) -> Matched | H81: =IF(ISNUMBER(F81),ROUND(E81-F81,2),"") -> 0
A82: 46191 | B82: 1010 Cash — Operating | C82: Telus network build — milestone | D82: REF40260 | E82: 47196.48 | F82: =_xlfn.XLOOKUP(Cash[[#This Row],[DocNo]],bank_statement_jun2026!C:C,bank_statement_jun2026!D:D,"Not Found") -> 47196.48 | G82: =IF(F82="Not Found","Missing from Bank",IF(ROUND(E82,2)=ROUND(F82,2),"Matched","Difference")) -> Matched | H82: =IF(ISNUMBER(F82),ROUND(E82-F82,2),"") -> 0
A83: 46192 | B83: 1010 Cash — Operating | C83: ADP Payroll — invoice payment | D83: CHQ#1066 | E83: -2934.68 | F83: =_xlfn.XLOOKUP(Cash[[#This Row],[DocNo]],bank_statement_jun2026!C:C,bank_statement_jun2026!D:D,"Not Found") -> -2934.68 | G83: =IF(F83="Not Found","Missing from Bank",IF(ROUND(E83,2)=ROUND(F83,2),"Matched","Difference")) -> Matched | H83: =IF(ISNUMBER(F83),ROUND(E83-F83,2),"") -> 0
A84: 46192 | B84: 1010 Cash — Operating | C84: Bell aerial build — holdback release | D84: REF40504 | E84: 30144.87 | F84: =_xlfn.XLOOKUP(Cash[[#This Row],[DocNo]],bank_statement_jun2026!C:C,bank_statement_jun2026!D:D,"Not Found") -> 30144.87 | G84: =IF(F84="Not Found","Missing from Bank",IF(ROUND(E84,2)=ROUND(F84,2),"Matched","Difference")) -> Matched | H84: =IF(ISNUMBER(F84),ROUND(E84-F84,2),"") -> 0
A85: 46192 | B85: 1010 Cash — Operating | C85: Brandt Tractor Ltd — invoice payment | D85: REF40408 | E85: -17410.26 | F85: =_xlfn.XLOOKUP(Cash[[#This Row],[DocNo]],bank_statement_jun2026!C:C,bank_statement_jun2026!D:D,"Not Found") -> -17410.26 | G85: =IF(F85="Not Found","Missing from Bank",IF(ROUND(E85,2)=ROUND(F85,2),"Matched","Difference")) -> Matched | H85: =IF(ISNUMBER(F85),ROUND(E85-F85,2),"") -> 0
A86: 46192 | B86: 1010 Cash — Operating | C86: Milton Hydro — invoice payment | D86: REF40918 | E86: -1154.82 | F86: =_xlfn.XLOOKUP(Cash[[#This Row],[DocNo]],bank_statement_jun2026!C:C,bank_statement_jun2026!D:D,"Not Found") -> -1154.68 | G86: =IF(F86="Not Found","Missing from Bank",IF(ROUND(E86,2)=ROUND(F86,2),"Matched","Difference")) -> Difference | H86: =IF(ISNUMBER(F86),ROUND(E86-F86,2),"") -> -0.14 | I86: Verify source and adjust GL to bank amount; GL–bank variance -$0.14
A87: 46192 | B87: 1010 Cash — Operating | C87: Region of Halton — invoice payment | D87: REF40270 | E87: -10385.29 | F87: =_xlfn.XLOOKUP(Cash[[#This Row],[DocNo]],bank_statement_jun2026!C:C,bank_statement_jun2026!D:D,"Not Found") -> -10385.29 | G87: =IF(F87="Not Found","Missing from Bank",IF(ROUND(E87,2)=ROUND(F87,2),"Matched","Difference")) -> Matched | H87: =IF(ISNUMBER(F87),ROUND(E87-F87,2),"") -> 0
A88: 46192 | B88: 1010 Cash — Operating | C88: Vermeer Canada — invoice payment | D88: REF40547 | E88: -14976.01 | F88: =_xlfn.XLOOKUP(Cash[[#This Row],[DocNo]],bank_statement_jun2026!C:C,bank_statement_jun2026!D:D,"Not Found") -> -14976.01 | G88: =IF(F88="Not Found","Missing from Bank",IF(ROUND(E88,2)=ROUND(F88,2),"Matched","Difference")) -> Matched | H88: =IF(ISNUMBER(F88),ROUND(E88-F88,2),"") -> 0
A89: 46195 | B89: 1010 Cash — Operating | C89: Anixter Canada — invoice payment | D89: CHQ#1069 | E89: -7966.03 | F89: =_xlfn.XLOOKUP(Cash[[#This Row],[DocNo]],bank_statement_jun2026!C:C,bank_statement_jun2026!D:D,"Not Found") -> -7966.03 | G89: =IF(F89="Not Found","Missing from Bank",IF(ROUND(E89,2)=ROUND(F89,2),"Matched","Difference")) -> Matched | H89: =IF(ISNUMBER(F89),ROUND(E89-F89,2),"") -> 0
A90: 46195 | B90: 1010 Cash — Operating | C90: Anixter Canada — invoice payment | D90: REF40901 | E90: -9274.16 | F90: =_xlfn.XLOOKUP(Cash[[#This Row],[DocNo]],bank_statement_jun2026!C:C,bank_statement_jun2026!D:D,"Not Found") -> -9274.79 | G90: =IF(F90="Not Found","Missing from Bank",IF(ROUND(E90,2)=ROUND(F90,2),"Matched","Difference")) -> Difference | H90: =IF(ISNUMBER(F90),ROUND(E90-F90,2),"") -> 0.63 | I90: Verify source and adjust GL to bank amount; GL–bank variance $0.63
A91: 46195 | B91: 1010 Cash — Operating | C91: Bell Canada — invoice payment | D91: CHQ#1061 | E91: -13390.63 | F91: =_xlfn.XLOOKUP(Cash[[#This Row],[DocNo]],bank_statement_jun2026!C:C,bank_statement_jun2026!D:D,"Not Found") -> -13390.63 | G91: =IF(F91="Not Found","Missing from Bank",IF(ROUND(E91,2)=ROUND(F91,2),"Matched","Difference")) -> Matched | H91: =IF(ISNUMBER(F91),ROUND(E91-F91,2),"") -> 0
A92: 46195 | B92: 1010 Cash — Operating | C92: Cogeco underground build | D92: REF40229 | E92: 59150.99 | F92: =_xlfn.XLOOKUP(Cash[[#This Row],[DocNo]],bank_statement_jun2026!C:C,bank_statement_jun2026!D:D,"Not Found") -> 59150.99 | G92: =IF(F92="Not Found","Missing from Bank",IF(ROUND(E92,2)=ROUND(F92,2),"Matched","Difference")) -> Matched | H92: =IF(ISNUMBER(F92),ROUND(E92-F92,2),"") -> 0
A93: 46195 | B93: 1010 Cash — Operating | C93: Ditch Witch of Ontario — invoice payment | D93: REF40249 | E93: -9603.95 | F93: =_xlfn.XLOOKUP(Cash[[#This Row],[DocNo]],bank_statement_jun2026!C:C,bank_statement_jun2026!D:D,"Not Found") -> -9603.95 | G93: =IF(F93="Not Found","Missing from Bank",IF(ROUND(E93,2)=ROUND(F93,2),"Matched","Difference")) -> Matched | H93: =IF(ISNUMBER(F93),ROUND(E93-F93,2),"") -> 0
A94: 46195 | B94: 1010 Cash — Operating | C94: Enterprise Fleet Mgmt — invoice payment | D94: REF40181 | E94: -19936.42 | F94: =_xlfn.XLOOKUP(Cash[[#This Row],[DocNo]],bank_statement_jun2026!C:C,bank_statement_jun2026!D:D,"Not Found") -> -19936.42 | G94: =IF(F94="Not Found","Missing from Bank",IF(ROUND(E94,2)=ROUND(F94,2),"Matched","Difference")) -> Matched | H94: =IF(ISNUMBER(F94),ROUND(E94-F94,2),"") -> 0
A95: 46195 | B95: 1010 Cash — Operating | C95: Enterprise Fleet Mgmt — invoice payment | D95: REF40801 | E95: -12259.66 | F95: =_xlfn.XLOOKUP(Cash[[#This Row],[DocNo]],bank_statement_jun2026!C:C,bank_statement_jun2026!D:D,"Not Found") -> -12259.66 | G95: =IF(F95="Not Found","Missing from Bank",IF(ROUND(E95,2)=ROUND(F95,2),"Matched","Difference")) -> Matched | H95: =IF(ISNUMBER(F95),ROUND(E95-F95,2),"") -> 0
A96: 46195 | B96: 1010 Cash — Operating | C96: Region of Halton — invoice payment | D96: CHQ#1059 | E96: -14341.45 | F96: =_xlfn.XLOOKUP(Cash[[#This Row],[DocNo]],bank_statement_jun2026!C:C,bank_statement_jun2026!D:D,"Not Found") -> -14341.45 | G96: =IF(F96="Not Found","Missing from Bank",IF(ROUND(E96,2)=ROUND(F96,2),"Matched","Difference")) -> Matched | H96: =IF(ISNUMBER(F96),ROUND(E96-F96,2),"") -> 0
A97: 46195 | B97: 1010 Cash — Operating | C97: Vermeer Canada — invoice payment | D97: CHQ#1075 | E97: -7694.16 | F97: =_xlfn.XLOOKUP(Cash[[#This Row],[DocNo]],bank_statement_jun2026!C:C,bank_statement_jun2026!D:D,"Not Found") -> -7694.16 | G97: =IF(F97="Not Found","Missing from Bank",IF(ROUND(E97,2)=ROUND(F97,2),"Matched","Difference")) -> Matched | H97: =IF(ISNUMBER(F97),ROUND(E97-F97,2),"") -> 0
A98: 46195 | B98: 1010 Cash — Operating | C98: WSIB Ontario — invoice payment | D98: REF40608 | E98: -18548.06 | F98: =_xlfn.XLOOKUP(Cash[[#This Row],[DocNo]],bank_statement_jun2026!C:C,bank_statement_jun2026!D:D,"Not Found") -> -18548.06 | G98: =IF(F98="Not Found","Missing from Bank",IF(ROUND(E98,2)=ROUND(F98,2),"Matched","Difference")) -> Matched | H98: =IF(ISNUMBER(F98),ROUND(E98-F98,2),"") -> 0
A99: 46196 | B99: 1010 Cash — Operating | C99: Intact Insurance — invoice payment | D99: REF40884 | E99: -1887.53 | F99: =_xlfn.XLOOKUP(Cash[[#This Row],[DocNo]],bank_statement_jun2026!C:C,bank_statement_jun2026!D:D,"Not Found") -> -1887.08 | G99: =IF(F99="Not Found","Missing from Bank",IF(ROUND(E99,2)=ROUND(F99,2),"Matched","Difference")) -> Difference | H99: =IF(ISNUMBER(F99),ROUND(E99-F99,2),"") -> -0.45 | I99: Verify source and adjust GL to bank amount; GL–bank variance -$0.45
A100: 46196 | B100: 1010 Cash — Operating | C100: Telecon Design — invoice payment | D100: REF40618 | E100: -22691.11 | F100: =_xlfn.XLOOKUP(Cash[[#This Row],[DocNo]],bank_statement_jun2026!C:C,bank_statement_jun2026!D:D,"Not Found") -> -22691.11 | G100: =IF(F100="Not Found","Missing from Bank",IF(ROUND(E100,2)=ROUND(F100,2),"Matched","Difference")) -> Matched | H100: =IF(ISNUMBER(F100),ROUND(E100-F100,2),"") -> 0
A101: 46196 | B101: 1010 Cash — Operating | C101: United Rentals — invoice payment | D101: REF40865 | E101: -6648.91 | F101: =_xlfn.XLOOKUP(Cash[[#This Row],[DocNo]],bank_statement_jun2026!C:C,bank_statement_jun2026!D:D,"Not Found") -> -6649.18 | G101: =IF(F101="Not Found","Missing from Bank",IF(ROUND(E101,2)=ROUND(F101,2),"Matched","Difference")) -> Difference | H101: =IF(ISNUMBER(F101),ROUND(E101-F101,2),"") -> 0.27 | I101: Verify source and adjust GL to bank amount; GL–bank variance $0.27
A102: 46197 | B102: 1010 Cash — Operating | C102: ADP Payroll — invoice payment | D102: REF40752 | E102: -10531.31 | F102: =_xlfn.XLOOKUP(Cash[[#This Row],[DocNo]],bank_statement_jun2026!C:C,bank_statement_jun2026!D:D,"Not Found") -> -10531.31 | G102: =IF(F102="Not Found","Missing from Bank",IF(ROUND(E102,2)=ROUND(F102,2),"Matched","Difference")) -> Matched | H102: =IF(ISNUMBER(F102),ROUND(E102-F102,2),"") -> 0
A103: 46197 | B103: 1010 Cash — Operating | C103: Bell Canada — invoice payment | D103: REF40314 | E103: -22899.9 | F103: =_xlfn.XLOOKUP(Cash[[#This Row],[DocNo]],bank_statement_jun2026!C:C,bank_statement_jun2026!D:D,"Not Found") -> -22899.9 | G103: =IF(F103="Not Found","Missing from Bank",IF(ROUND(E103,2)=ROUND(F103,2),"Matched","Difference")) -> Matched | H103: =IF(ISNUMBER(F103),ROUND(E103-F103,2),"") -> 0
A104: 46197 | B104: 1010 Cash — Operating | C104: Milton Hydro — invoice payment | D104: REF40780 | E104: -16540.94 | F104: =_xlfn.XLOOKUP(Cash[[#This Row],[DocNo]],bank_statement_jun2026!C:C,bank_statement_jun2026!D:D,"Not Found") -> -16540.94 | G104: =IF(F104="Not Found","Missing from Bank",IF(ROUND(E104,2)=ROUND(F104,2),"Matched","Difference")) -> Matched | H104: =IF(ISNUMBER(F104),ROUND(E104-F104,2),"") -> 0
A105: 46197 | B105: 1010 Cash — Operating | C105: Rogers Communications — progress billing | D105: REF40425 | E105: 30455.14 | F105: =_xlfn.XLOOKUP(Cash[[#This Row],[DocNo]],bank_statement_jun2026!C:C,bank_statement_jun2026!D:D,"Not Found") -> 30455.14 | G105: =IF(F105="Not Found","Missing from Bank",IF(ROUND(E105,2)=ROUND(F105,2),"Matched","Difference")) -> Matched | H105: =IF(ISNUMBER(F105),ROUND(E105-F105,2),"") -> 0
A106: 46198 | B106: 1010 Cash — Operating | C106: Brandt Tractor Ltd — invoice payment | D106: REF40163 | E106: -5308.77 | F106: =_xlfn.XLOOKUP(Cash[[#This Row],[DocNo]],bank_statement_jun2026!C:C,bank_statement_jun2026!D:D,"Not Found") -> -5308.77 | G106: =IF(F106="Not Found","Missing from Bank",IF(ROUND(E106,2)=ROUND(F106,2),"Matched","Difference")) -> Matched | H106: =IF(ISNUMBER(F106),ROUND(E106-F106,2),"") -> 0
A107: 46198 | B107: 1010 Cash — Operating | C107: Ditch Witch of Ontario — invoice payment | D107: REF40348 | E107: -19617.67 | F107: =_xlfn.XLOOKUP(Cash[[#This Row],[DocNo]],bank_statement_jun2026!C:C,bank_statement_jun2026!D:D,"Not Found") -> -19617.67 | G107: =IF(F107="Not Found","Missing from Bank",IF(ROUND(E107,2)=ROUND(F107,2),"Matched","Difference")) -> Matched | H107: =IF(ISNUMBER(F107),ROUND(E107-F107,2),"") -> 0
A108: 46198 | B108: 1010 Cash — Operating | C108: Vermeer Canada — invoice payment | D108: REF40542 | E108: -7711.34 | F108: =_xlfn.XLOOKUP(Cash[[#This Row],[DocNo]],bank_statement_jun2026!C:C,bank_statement_jun2026!D:D,"Not Found") -> -7711.34 | G108: =IF(F108="Not Found","Missing from Bank",IF(ROUND(E108,2)=ROUND(F108,2),"Matched","Difference")) -> Matched | H108: =IF(ISNUMBER(F108),ROUND(E108-F108,2),"") -> 0
A109: 46198 | B109: 1010 Cash — Operating | C109: WSIB Ontario — invoice payment | D109: CHQ#1045 | E109: -20256.73 | F109: =_xlfn.XLOOKUP(Cash[[#This Row],[DocNo]],bank_statement_jun2026!C:C,bank_statement_jun2026!D:D,"Not Found") -> -20256.73 | G109: =IF(F109="Not Found","Missing from Bank",IF(ROUND(E109,2)=ROUND(F109,2),"Matched","Difference")) -> Matched | H109: =IF(ISNUMBER(F109),ROUND(E109-F109,2),"") -> 0
A110: 46199 | B110: 1010 Cash — Operating | C110: Brandt Tractor Ltd — invoice payment | D110: REF40281 | E110: -15125.76 | F110: =_xlfn.XLOOKUP(Cash[[#This Row],[DocNo]],bank_statement_jun2026!C:C,bank_statement_jun2026!D:D,"Not Found") -> -15125.76 | G110: =IF(F110="Not Found","Missing from Bank",IF(ROUND(E110,2)=ROUND(F110,2),"Matched","Difference")) -> Matched | H110: =IF(ISNUMBER(F110),ROUND(E110-F110,2),"") -> 0
A111: 46199 | B111: 1010 Cash — Operating | C111: Ditch Witch of Ontario — parts invoice | D111: CHQ#1079 | E111: -7412.66 | F111: =_xlfn.XLOOKUP(Cash[[#This Row],[DocNo]],bank_statement_jun2026!C:C,bank_statement_jun2026!D:D,"Not Found") -> Not Found | G111: =IF(F111="Not Found","Missing from Bank",IF(ROUND(E111,2)=ROUND(F111,2),"Matched","Difference")) -> Missing from Bank | H111: =IF(ISNUMBER(F111),ROUND(E111-F111,2),"") | I111: Outstanding payment—confirm it cleared after June
A112: 46199 | B112: 1010 Cash — Operating | C112: Petro-Canada SuperPass — invoice payment | D112: REF40482 | E112: -22249.66 | F112: =_xlfn.XLOOKUP(Cash[[#This Row],[DocNo]],bank_statement_jun2026!C:C,bank_statement_jun2026!D:D,"Not Found") -> -22249.66 | G112: =IF(F112="Not Found","Missing from Bank",IF(ROUND(E112,2)=ROUND(F112,2),"Matched","Difference")) -> Matched | H112: =IF(ISNUMBER(F112),ROUND(E112-F112,2),"") -> 0
A113: 46199 | B113: 1010 Cash — Operating | C113: Shell Fleet Card — invoice payment | D113: REF40675 | E113: -20774.91 | F113: =_xlfn.XLOOKUP(Cash[[#This Row],[DocNo]],bank_statement_jun2026!C:C,bank_statement_jun2026!D:D,"Not Found") -> -20774.91 | G113: =IF(F113="Not Found","Missing from Bank",IF(ROUND(E113,2)=ROUND(F113,2),"Matched","Difference")) -> Matched | H113: =IF(ISNUMBER(F113),ROUND(E113-F113,2),"") -> 0
A114: 46199 | B114: 1010 Cash — Operating | C114: Shell Fleet Card — invoice payment | D114: REF40706 | E114: -6535.31 | F114: =_xlfn.XLOOKUP(Cash[[#This Row],[DocNo]],bank_statement_jun2026!C:C,bank_statement_jun2026!D:D,"Not Found") -> -6535.31 | G114: =IF(F114="Not Found","Missing from Bank",IF(ROUND(E114,2)=ROUND(F114,2),"Matched","Difference")) -> Matched | H114: =IF(ISNUMBER(F114),ROUND(E114-F114,2),"") -> 0
A115: 46199 | B115: 1010 Cash — Operating | C115: United Rentals — invoice payment | D115: REF40341 | E115: -22311.13 | F115: =_xlfn.XLOOKUP(Cash[[#This Row],[DocNo]],bank_statement_jun2026!C:C,bank_statement_jun2026!D:D,"Not Found") -> -22311.13 | G115: =IF(F115="Not Found","Missing from Bank",IF(ROUND(E115,2)=ROUND(F115,2),"Matched","Difference")) -> Matched | H115: =IF(ISNUMBER(F115),ROUND(E115-F115,2),"") -> 0
A116: 46199 | B116: 1010 Cash — Operating | C116: Vermeer Canada — invoice payment | D116: REF40716 | E116: -8508.86 | F116: =_xlfn.XLOOKUP(Cash[[#This Row],[DocNo]],bank_statement_jun2026!C:C,bank_statement_jun2026!D:D,"Not Found") -> -8508.86 | G116: =IF(F116="Not Found","Missing from Bank",IF(ROUND(E116,2)=ROUND(F116,2),"Matched","Difference")) -> Matched | H116: =IF(ISNUMBER(F116),ROUND(E116-F116,2),"") -> 0
A117: 46199 | B117: 1010 Cash — Operating | C117: WESCO Distribution — invoice payment | D117: REF40852 | E117: -13902.44 | F117: =_xlfn.XLOOKUP(Cash[[#This Row],[DocNo]],bank_statement_jun2026!C:C,bank_statement_jun2026!D:D,"Not Found") -> -13902.08 | G117: =IF(F117="Not Found","Missing from Bank",IF(ROUND(E117,2)=ROUND(F117,2),"Matched","Difference")) -> Difference | H117: =IF(ISNUMBER(F117),ROUND(E117-F117,2),"") -> -0.36 | I117: Verify source and adjust GL to bank amount; GL–bank variance -$0.36
A118: 46202 | B118: 1010 Cash — Operating | C118: Region of Halton — road permit fees | D118: CHQ#1081 | E118: -2340.55 | F118: =_xlfn.XLOOKUP(Cash[[#This Row],[DocNo]],bank_statement_jun2026!C:C,bank_statement_jun2026!D:D,"Not Found") -> Not Found | G118: =IF(F118="Not Found","Missing from Bank",IF(ROUND(E118,2)=ROUND(F118,2),"Matched","Difference")) -> Missing from Bank | H118: =IF(ISNUMBER(F118),ROUND(E118-F118,2),"") | I118: Outstanding payment—confirm it cleared after June
A119: 46202 | B119: 1010 Cash — Operating | C119: Vermeer Canada — drill head rebuild | D119: CHQ#1080 | E119: -15890.23 | F119: =_xlfn.XLOOKUP(Cash[[#This Row],[DocNo]],bank_statement_jun2026!C:C,bank_statement_jun2026!D:D,"Not Found") -> Not Found | G119: =IF(F119="Not Found","Missing from Bank",IF(ROUND(E119,2)=ROUND(F119,2),"Matched","Difference")) -> Missing from Bank | H119: =IF(ISNUMBER(F119),ROUND(E119-F119,2),"") | I119: Outstanding payment—confirm it cleared after June
A120: 46203 | B120: 1010 Cash — Operating | C120: Brandt Tractor Ltd — service invoice | D120: CHQ#1082 | E120: -4178.09 | F120: =_xlfn.XLOOKUP(Cash[[#This Row],[DocNo]],bank_statement_jun2026!C:C,bank_statement_jun2026!D:D,"Not Found") -> Not Found | G120: =IF(F120="Not Found","Missing from Bank",IF(ROUND(E120,2)=ROUND(F120,2),"Matched","Difference")) -> Missing from Bank | H120: =IF(ISNUMBER(F120),ROUND(E120-F120,2),"") | I120: Outstanding payment—confirm it cleared after June
A121: 46203 | B121: 1010 Cash — Operating | C121: Cogeco underground build | D121: REF40957 | E121: 12764.31 | F121: =_xlfn.XLOOKUP(Cash[[#This Row],[DocNo]],bank_statement_jun2026!C:C,bank_statement_jun2026!D:D,"Not Found") -> Not Found | G121: =IF(F121="Not Found","Missing from Bank",IF(ROUND(E121,2)=ROUND(F121,2),"Matched","Difference")) -> Missing from Bank | H121: =IF(ISNUMBER(F121),ROUND(E121-F121,2),"") | I121: Deposit in transit—confirm bank receipt after June
A122: 46203 | B122: 1010 Cash — Operating | C122: Rogers Communications — progress billing | D122: REF40947 | E122: 48310.77 | F122: =_xlfn.XLOOKUP(Cash[[#This Row],[DocNo]],bank_statement_jun2026!C:C,bank_statement_jun2026!D:D,"Not Found") -> Not Found | G122: =IF(F122="Not Found","Missing from Bank",IF(ROUND(E122,2)=ROUND(F122,2),"Matched","Difference")) -> Missing from Bank | H122: =IF(ISNUMBER(F122),ROUND(E122-F122,2),"") | I122: Deposit in transit—confirm bank receipt after June
D124: Full GL Activity Total | E124: =SUM(Cash[Amount]) -> 253663.77 | G124: Net Amount Difference | H124: =SUM(Cash[Difference Amount]) -> 0.35
